aiocdek/__init__.py
aiocdek/api/__init__.py
aiocdek/api/calculator.py
aiocdek/api/courier.py
aiocdek/api/delivery_points.py
aiocdek/api/locations.py
aiocdek/api/orders.py
aiocdek/api/printing.py
aiocdek/api/webhooks.py
aiocdek/client/__init__.py
aiocdek/client/cdek.py
aiocdek/client/common.py
aiocdek/enums/__init__.py
aiocdek/enums/enums.py
aiocdek/models/__init__.py
aiocdek/models/base.py
aiocdek/models/calculator.py
aiocdek/models/courier.py
aiocdek/models/delivery_points.py
aiocdek/models/locations.py
aiocdek/models/orders.py
aiocdek/models/printing.py
aiocdek/models/webhooks.py
aiocdek-0.1.7.dist-info/METADATA
aiocdek-0.1.7.dist-info/WHEEL
aiocdek-0.1.7.dist-info/licenses/LICENSE
aiocdek-0.1.7.dist-info/RECORD
