Metadata-Version: 2.4
Name: aiocdek
Version: 0.1.7
Summary: An asynchronous Python client library for the CDEK API
Project-URL: Homepage, https://github.com/plassstic/aiocdek
Project-URL: Repository, https://github.com/plassstic/aiocdek.git
Project-URL: Documentation, https://github.com/plassstic/aiocdek/blob/main/docs/API_REFERENCE.md
Project-URL: Bug Tracker, https://github.com/plassstic/aiocdek/issues
Author-email: "Alexey P." <i@apechenin.ru>
License-Expression: GPL-3.0
License-File: LICENSE
Keywords: api,async,cdek,courier,delivery,logistics,russia,shipping
Classifier: Development Status :: 4 - Beta
Classifier: Intended Audience :: Developers
Classifier: License :: OSI Approved :: GNU General Public License v3 (GPLv3)
Classifier: Operating System :: OS Independent
Classifier: Programming Language :: Python :: 3
Classifier: Programming Language :: Python :: 3.9
Classifier: Programming Language :: Python :: 3.10
Classifier: Programming Language :: Python :: 3.11
Classifier: Programming Language :: Python :: 3.12
Classifier: Topic :: Internet :: WWW/HTTP :: HTTP Servers
Classifier: Topic :: Office/Business
Classifier: Topic :: Software Development :: Libraries :: Python Modules
Classifier: Typing :: Typed
Requires-Python: >=3.9
Requires-Dist: aiohttp>=3.8.0
Requires-Dist: build>=1.3.0
Requires-Dist: loguru>=0.6.0
Requires-Dist: pydantic>=2.0.0
Requires-Dist: twine>=6.1.0
Provides-Extra: dev
Requires-Dist: black>=23.0.0; extra == 'dev'
Requires-Dist: build>=0.10.0; extra == 'dev'
Requires-Dist: flake8>=6.0.0; extra == 'dev'
Requires-Dist: isort>=5.12.0; extra == 'dev'
Requires-Dist: mypy>=1.0.0; extra == 'dev'
Requires-Dist: pytest-asyncio>=0.21.0; extra == 'dev'
Requires-Dist: pytest-cov>=4.0.0; extra == 'dev'
Requires-Dist: pytest>=7.0.0; extra == 'dev'
Requires-Dist: twine>=4.0.0; extra == 'dev'
